spotag/__init__.py
spotag/app.py
spotag/m4a.py
spotag/main.py
spotag/models.py
spotag/spotify.py
spotag-0.1.0.dist-info/METADATA
spotag-0.1.0.dist-info/WHEEL
spotag-0.1.0.dist-info/entry_points.txt
spotag-0.1.0.dist-info/top_level.txt
spotag-0.1.0.dist-info/RECORD
